clubhouse/__init__.py
clubhouse-0.3.0.dist-info/LICENSE
clubhouse-0.3.0.dist-info/WHEEL
clubhouse-0.3.0.dist-info/METADATA
clubhouse-0.3.0.dist-info/RECORD
