Metadata-Version: 2.1
Name: clubhouse
Version: 0.3.0
Summary: Client for the Clubhouse API
Home-page: https://github.com/j-martin/clubhouse-client
License: Apache-2.0
Author: Jean-Martin Archer
Author-email: jm@jmartin.ca
Requires-Python: >=3.7,<4.0
Classifier: License :: OSI Approved :: Apache Software License
Classifier: Programming Language :: Python :: 3
Classifier: Programming Language :: Python :: 3.7
Classifier: Programming Language :: Python :: 3.8
Requires-Dist: requests (>=2.21,<3.0)
Project-URL: Repository, https://github.com/j-martin/clubhouse-client
